my_app/__init__.py
my_app/_version.py
my_app/jtpscraper.py
my_app/my_app.py
jtpdf-0.0.2.dist-info/METADATA
jtpdf-0.0.2.dist-info/WHEEL
jtpdf-0.0.2.dist-info/entry_points.txt
jtpdf-0.0.2.dist-info/top_level.txt
jtpdf-0.0.2.dist-info/RECORD
