Metadata-Version: 2.1
Name: jtpdf
Version: 0.0.2
Summary: A package to scrape the JavaTpoint for tuts and convert them to pdf.
Home-page: https://github.com/has12zen/javatpointScraper
Author: has12zen
Author-email: harshsapkal.sa@gmail.com
License: UNKNOWN
Platform: UNKNOWN
Classifier: Programming Language :: Python :: 3.8
Requires-Dist: beautifulsoup4 (>=4.4.0)
Requires-Dist: requests (>=2.7.0)
Requires-Dist: pdfkit (>=0.6.1)
